Workbook

Sheet Sales Data
A1: SALES & REVENUE TRACKER — FY 2024
A2: Data Entry Clerk: Viena Ouma | Prepared: March 2026 | All amounts in KES
A3: Order ID | B3: Date | C3: Sales Rep | D3: Region | E3: Product | F3: Category | G3: Units Sold | H3: Unit Price (KES) | I3: Gross Revenue (KES) | J3: Discount (%) | K3: Net Revenue (KES)
A4: ORD-001 | B4: 2024-01-05 | C4: Alice Kamau | D4: Nairobi | E4: Laptop Pro 15 | F4: Electronics | G4: 8 | H4: 95000 | I4: =G4*H4 -> 760000 | J4: 0.05 | K4: =I4*(1-J4) -> 722000
A5: ORD-002 | B5: 2024-01-12 | C5: Brian Otieno | D5: Mombasa | E5: Office Chair X2 | F5: Furniture | G5: 15 | H5: 12500 | I5: =G5*H5 -> 187500 | J5: 0.08 | K5: =I5*(1-J5) -> 172500
A6: ORD-003 | B6: 2024-01-20 | C6: Carol Wanjiku | D6: Kisumu | E6: Wireless Mouse | F6: Accessories | G6: 40 | H6: 2200 | I6: =G6*H6 -> 88000 | J6: 0.03 | K6: =I6*(1-J6) -> 85360
A7: ORD-004 | B7: 2024-02-03 | C7: Alice Kamau | D7: Nairobi | E7: Monitor 27" | F7: Electronics | G7: 6 | H7: 38000 | I7: =G7*H7 -> 228000 | J7: 0.05 | K7: =I7*(1-J7) -> 216600
A8: ORD-005 | B8: 2024-02-14 | C8: David Mwangi | D8: Nakuru | E8: Standing Desk | F8: Furniture | G8: 9 | H8: 28000 | I8: =G8*H8 -> 252000 | J8: 0.08 | K8: =I8*(1-J8) -> 231840
A9: ORD-006 | B9: 2024-02-28 | C9: Brian Otieno | D9: Mombasa | E9: Laptop Pro 15 | F9: Electronics | G9: 5 | H9: 95000 | I9: =G9*H9 -> 475000 | J9: 0.05 | K9: =I9*(1-J9) -> 451250
A10: ORD-007 | B10: 2024-03-07 | C10: Carol Wanjiku | D10: Kisumu | E10: Keyboard Mech | F10: Accessories | G10: 25 | H10: 5500 | I10: =G10*H10 -> 137500 | J10: 0.03 | K10: =I10*(1-J10) -> 133375
A11: ORD-008 | B11: 2024-03-15 | C11: David Mwangi | D11: Nakuru | E11: Monitor 27" | F11: Electronics | G11: 4 | H11: 38000 | I11: =G11*H11 -> 152000 | J11: 0.05 | K11: =I11*(1-J11) -> 144400
A12: ORD-009 | B12: 2024-04-02 | C12: Alice Kamau | D12: Nairobi | E12: Office Chair X2 | F12: Furniture | G12: 20 | H12: 12500 | I12: =G12*H12 -> 250000 | J12: 0.08 | K12: =I12*(1-J12) -> 230000
A13: ORD-010 | B13: 2024-04-18 | C13: Brian Otieno | D13: Mombasa | E13: Wireless Mouse | F13: Accessories | G13: 60 | H13: 2200 | I13: =G13*H13 -> 132000 | J13: 0.03 | K13: =I13*(1-J13) -> 128040
A14: ORD-011 | B14: 2024-05-09 | C14: Carol Wanjiku | D14: Kisumu | E14: Laptop Pro 15 | F14: Electronics | G14: 3 | H14: 95000 | I14: =G14*H14 -> 285000 | J14: 0.05 | K14: =I14*(1-J14) -> 270750
A15: ORD-012 | B15: 2024-05-22 | C15: David Mwangi | D15: Nakuru | E15: Keyboard Mech | F15: Accessories | G15: 30 | H15: 5500 | I15: =G15*H15 -> 165000 | J15: 0.03 | K15: =I15*(1-J15) -> 160050
... A29: ORD-026 | B29: 2024-12-22 | C29: Brian Otieno | D29: Mombasa | E29: Keyboard Mech | F29: Accessories | G29: 28 | H29: 5500 | I29: =G29*H29 -> 154000 | J29: 0.03 | K29: =I29*(1-J29) -> 149380
A30: TOTALS | G30: =SUM(G4:G29) -> 466 | I30: =SUM(I4:I29) -> 6795500 | K30: =SUM(K4:K29) -> 6426030

Sheet Summary Dashboard
A1: SALES SUMMARY DASHBOARD — FY 2024
A2: Auto-calculated from Sales Data sheet
A4: Total Orders | C4: Total Units Sold | E4: Total Gross Rev (KES) | G4: Total Net Rev (KES)
A5: =COUNTA('Sales Data'!A4:A29) -> 26 | C5: =SUM('Sales Data'!G4:G29) -> 466 | E5: =SUM('Sales Data'!I4:I29) -> 6795500 | G5: =SUM('Sales Data'!K4:K29) -> 6426030
A7: Region | B7: Total Orders | C7: Gross Revenue (KES) | D7: Net Revenue (KES) | E7: Avg Net/Order (KES)
A8: Nairobi | B8: =COUNTIF('Sales Data'!D4:D29,"Nairobi") -> 7 | C8: =SUMIF('Sales Data'!D4:D29,"Nairobi",'Sales Data'!I4:I29) -> 2973000 | D8: =SUMIF('Sales Data'!D4:D29,"Nairobi",'Sales Data'!K4:K29) -> 2810970 | E8: =IF(B8=0,0,D8/B8) -> 401567.14
A9: Mombasa | B9: =COUNTIF('Sales Data'!D4:D29,"Mombasa") -> 7 | C9: =SUMIF('Sales Data'!D4:D29,"Mombasa",'Sales Data'!I4:I29) -> 1405500 | D9: =SUMIF('Sales Data'!D4:D29,"Mombasa",'Sales Data'!K4:K29) -> 1332260 | E9: =IF(B9=0,0,D9/B9) -> 190322.86
A10: Kisumu | B10: =COUNTIF('Sales Data'!D4:D29,"Kisumu") -> 6 | C10: =SUMIF('Sales Data'!D4:D29,"Kisumu",'Sales Data'!I4:I29) -> 1078000 | D10: =SUMIF('Sales Data'!D4:D29,"Kisumu",'Sales Data'!K4:K29) -> 1021210 | E10: =IF(B10=0,0,D10/B10) -> 170201.67
A11: Nakuru | B11: =COUNTIF('Sales Data'!D4:D29,"Nakuru") -> 6 | C11: =SUMIF('Sales Data'!D4:D29,"Nakuru",'Sales Data'!I4:I29) -> 1339000 | D11: =SUMIF('Sales Data'!D4:D29,"Nakuru",'Sales Data'!K4:K29) -> 1261590 | E11: =IF(B11=0,0,D11/B11) -> 210265
A12: TOTAL | B12: =SUM(B8:B11) -> 26 | C12: =SUM(C8:C11) -> 6795500 | D12: =SUM(D8:D11) -> 6426030 | E12: =SUM(E8:E11) -> 972356.67
A14: Category | B14: Total Orders | C14: Gross Revenue (KES) | D14: Net Revenue (KES) | E14: Discount Rate
A15: Electronics | B15: =COUNTIF('Sales Data'!F4:F29,"Electronics") -> 10 | C15: =SUMIF('Sales Data'!F4:F29,"Electronics",'Sales Data'!I4:I29) -> 4009000 | D15: =SUMIF('Sales Data'!F4:F29,"Electronics",'Sales Data'!K4:K29) -> 3808550 | E15: 5%
A16: Furniture | B16: =COUNTIF('Sales Data'!F4:F29,"Furniture") -> 8 | C16: =SUMIF('Sales Data'!F4:F29,"Furniture",'Sales Data'!I4:I29) -> 1708500 | D16: =SUMIF('Sales Data'!F4:F29,"Furniture",'Sales Data'!K4:K29) -> 1571820 | E16: 8%
A17: Accessories | B17: =COUNTIF('Sales Data'!F4:F29,"Accessories") -> 8 | C17: =SUMIF('Sales Data'!F4:F29,"Accessories",'Sales Data'!I4:I29) -> 1078000 | D17: =SUMIF('Sales Data'!F4:F29,"Accessories",'Sales Data'!K4:K29) -> 1045660 | E17: 3%
A18: TOTAL | B18: =SUM(B15:B17) -> 26 | C18: =SUM(C15:C17) -> 6795500 | D18: =SUM(D15:D17) -> 6426030
A20: Sales Rep | B20: Total Orders | C20: Gross Revenue (KES) | D20: Net Revenue (KES)
A21: Alice Kamau | B21: =COUNTIF('Sales Data'!C4:C29,"Alice Kamau") -> 7 | C21: =SUMIF('Sales Data'!C4:C29,"Alice Kamau",'Sales Data'!I4:I29) -> 2973000 | D21: =SUMIF('Sales Data'!C4:C29,"Alice Kamau",'Sales Data'!K4:K29) -> 2810970
A22: Brian Otieno | B22: =COUNTIF('Sales Data'!C4:C29,"Brian Otieno") -> 7 | C22: =SUMIF('Sales Data'!C4:C29,"Brian Otieno",'Sales Data'!I4:I29) -> 1405500 | D22: =SUMIF('Sales Data'!C4:C29,"Brian Otieno",'Sales Data'!K4:K29) -> 1332260
A23: Carol Wanjiku | B23: =COUNTIF('Sales Data'!C4:C29,"Carol Wanjiku") -> 6 | C23: =SUMIF('Sales Data'!C4:C29,"Carol Wanjiku",'Sales Data'!I4:I29) -> 1078000 | D23: =SUMIF('Sales Data'!C4:C29,"Carol Wanjiku",'Sales Data'!K4:K29) -> 1021210
A24: David Mwangi | B24: =COUNTIF('Sales Data'!C4:C29,"David Mwangi") -> 6 | C24: =SUMIF('Sales Data'!C4:C29,"David Mwangi",'Sales Data'!I4:I29) -> 1339000 | D24: =SUMIF('Sales Data'!C4:C29,"David Mwangi",'Sales Data'!K4:K29) -> 1261590
A25: TOTAL | B25: =SUM(B21:B24) -> 26 | C25: =SUM(C21:C24) -> 6795500 | D25: =SUM(D21:D24) -> 6426030

Sheet Verification Log
A1: DATA VERIFICATION & QUALITY CHECK LOG
A2: CHECK | B2: DESCRIPTION | C2: RESULT | D2: DETAILS | E2: STATUS
A3: Duplicate Order IDs | B3: Verify all Order IDs are unique | C3: PASSED | D3: 26 unique IDs, 0 duplicates found | E3: ✔
A4: Date Range Validity | B4: All dates fall within FY 2024 | C4: PASSED | D4: Range: 2024-01-05 to 2024-12-22 | E4: ✔
A5: Missing Values | B5: Check for blank cells in required fields | C5: PASSED | D5: No blank cells detected in cols A–H | E5: ✔
A6: Unit Price Consistency | B6: Same product = same unit price | C6: PASSED | D6: Prices verified against product master list | E6: ✔
A7: Formula Accuracy (Gross) | B7: Gross = Units × Unit Price | C7: PASSED | D7: All 26 rows verified; 0 formula errors | E7: ✔
A8: Formula Accuracy (Net) | B8: Net = Gross × (1 – Discount) | C8: PASSED | D8: All 26 rows verified; 0 formula errors | E8: ✔
A9: Discount Rate Consistency | B9: Category-level discount applied correctly | C9: PASSED | D9: Elec 5%, Furn 8%, Access 3% — confirmed | E9: ✔
A10: Negative Revenue Check | B10: No negative revenue values | C10: PASSED | D10: MIN(Net Revenue) > 0 confirmed | E10: ✔
A11: Region Spelling | B11: Standardised region names | C11: PASSED | D11: 4 regions: Nairobi, Mombasa, Kisumu, Nakuru | E11: ✔
A12: Summary Tie-Out | B12: Dashboard totals match raw data totals | C12: PASSED | D12: Gross & Net sums reconciled across sheets | E12: ✔
A15: VERIFIED BY: Viena Ouma | ROLE: Remote Data Entry Clerk | DATE: March 2026
